sqlalchemy_dantic/__init__.py
sqlalchemy_dantic/main.py
sqlalchemy_dantic-0.2.0.dist-info/LICENSE
sqlalchemy_dantic-0.2.0.dist-info/WHEEL
sqlalchemy_dantic-0.2.0.dist-info/METADATA
sqlalchemy_dantic-0.2.0.dist-info/RECORD
