Metadata-Version: 2.1
Name: sqlalchemy-dantic
Version: 0.2.0
Summary: Tools to convert SQLAlchemy models to Pydantic models.Thanks project 'pydantic-sqlalchemy'.
License: MIT
Author: Chise1
Author-email: chise123@live.com
Requires-Python: >=3.6,<4.0
Classifier: License :: OSI Approved :: MIT License
Classifier: Programming Language :: Python :: 3
Classifier: Programming Language :: Python :: 3.6
Classifier: Programming Language :: Python :: 3.7
Classifier: Programming Language :: Python :: 3.8
Classifier: Programming Language :: Python :: 3.9
Requires-Dist: pydantic (>=1.5.1,<2.0.0)
Requires-Dist: sqlalchemy (>=1.3.16,<2.0.0)
